text_region_parser/__init__.py
text_region_parser/_utils.py
text_region_parser/options.py
text_region_parser/py.typed
text_region_parser/region_class.py
text_region_parser/region_constructor.py
text_region_parser/region_parser.py
text_region_parser-0.1.0.dist-info/METADATA
text_region_parser-0.1.0.dist-info/WHEEL
text_region_parser-0.1.0.dist-info/licenses/LICENCE
text_region_parser-0.1.0.dist-info/RECORD
