Metadata-Version: 2.4
Name: text-region-parser
Version: 0.1.0
Summary: Add your description here
Author-email: Jag_k <30597878+jag-k@users.noreply.github.com>
License-File: LICENCE
Requires-Python: >=3.9
Requires-Dist: typing-extensions; python_version < '3.10'
